timerr/__init__.py
timerr-1.0.4.dist-info/LICENSE
timerr-1.0.4.dist-info/METADATA
timerr-1.0.4.dist-info/WHEEL
timerr-1.0.4.dist-info/top_level.txt
timerr-1.0.4.dist-info/RECORD
