Metadata-Version: 2.1
Name: timerr
Version: 1.0.4
Summary: A basic timer that counts down from time entered
Home-page: https://github.com/ItzAfroBoy/timerr
Author: ItzAfroBoy
Author-email: spareafro@post.com
License: MIT
Platform: UNKNOWN
